README.txt
setup.py
docs/HISTORY.txt
valentine/__init__.py
valentine.multiparagraphpage.egg-info/PKG-INFO
valentine.multiparagraphpage.egg-info/SOURCES.txt
valentine.multiparagraphpage.egg-info/dependency_links.txt
valentine.multiparagraphpage.egg-info/entry_points.txt
valentine.multiparagraphpage.egg-info/namespace_packages.txt
valentine.multiparagraphpage.egg-info/not-zip-safe
valentine.multiparagraphpage.egg-info/requires.txt
valentine.multiparagraphpage.egg-info/top_level.txt
valentine/multiparagraphpage/LINGUAPLONE.txt
valentine/multiparagraphpage/MIGRATION.txt
valentine/multiparagraphpage/README.txt
valentine/multiparagraphpage/__init__.py
valentine/multiparagraphpage/config.py
valentine/multiparagraphpage/configure.zcml
valentine/multiparagraphpage/browser/__init__.py
valentine/multiparagraphpage/browser/configure.zcml
valentine/multiparagraphpage/browser/manageparagraphs.pt
valentine/multiparagraphpage/browser/manageparagraphs.py
valentine/multiparagraphpage/browser/multiparagraphpage.gif
valentine/multiparagraphpage/browser/multiparagraphpage.kss
valentine/multiparagraphpage/browser/multiparagraphpage_view.pt
valentine/multiparagraphpage/browser/migration/__init__.py
valentine/multiparagraphpage/browser/migration/configure.zcml
valentine/multiparagraphpage/browser/migration/migrate.py
valentine/multiparagraphpage/content/__init__.py
valentine/multiparagraphpage/content/configure.zcml
valentine/multiparagraphpage/content/multiparagraphpage.py
valentine/multiparagraphpage/interfaces/__init__.py
valentine/multiparagraphpage/interfaces/multiparagraphpage.py
valentine/multiparagraphpage/profiles/default/factorytool.xml
valentine/multiparagraphpage/profiles/default/metadata.xml
valentine/multiparagraphpage/profiles/default/portlets.xml
valentine/multiparagraphpage/profiles/default/rolemap.xml
valentine/multiparagraphpage/profiles/default/skins.xml
valentine/multiparagraphpage/profiles/default/types.xml
valentine/multiparagraphpage/profiles/default/types/MultiParagraphPage.xml
valentine/multiparagraphpage/skins/multiparagraphpage_templates/1p2_view.pt
valentine/multiparagraphpage/skins/multiparagraphpage_templates/1p2_view.pt.metadata
valentine/multiparagraphpage/skins/multiparagraphpage_templates/2p2_view.pt
valentine/multiparagraphpage/skins/multiparagraphpage_templates/2p2_view.pt.metadata
valentine/multiparagraphpage/skins/multiparagraphpage_templates/2p3_view.pt
