Metadata-Version: 1.0
Name: valentine.multiparagraphpage
Version: 0.4
Summary: A page content type with multiple paragraphs(text bodies) without being folderish.
Home-page: http://svn.plone.org/svn/collective/valentine.multiparagraphpage/trunk/
Author: Sasha Vincic
Author-email: sasha dot vincic at valentinewebsystems dot se
License: GPL
Keywords: archetype,plone,richtext,multi paragrah
Platform: UNKNOWN
Classifier: Programming Language :: Python
